asynchronous_fifo.v
// ### ASYNCHRONOUS FIFO ###

// NOTE : I am doing all comparisions in gray itself rather than converting the gray process into binary 

module async_fifo (wr_clk,rd_clk,rst,wr_en,rd_en,wr_data,rd_data,full,empty) ;

input wr_clk,rd_clk,rst,wr_en,rd_en ;
input [7:0] wr_data ;
output reg [7:0] rd_data ;
output full,empty ;

reg [3:0] wr_ptr,rd_ptr;
wire [3:0] wr_ptr_gray,rd_ptr_gray ;

reg [7:0] mem [7:0] ; // FIFO

reg [3:0] wr_ptr_gray_ff1,wr_ptr_gray_ff2  ; // Synchronize read and write pointers ( Gray Code )
reg [3:0] wr_ptr_gray_sync ;
reg [3:0] rd_ptr_gray_ff1,rd_ptr_gray_ff2 ;
reg [3:0] rd_ptr_gray_sync ;

// ***** WRITE OPERATION *****
always @ (posedge wr_clk)
    begin
        if (rst)
            wr_ptr <= 4'b0 ;
        else
            begin
                if (wr_en && !full) 
                    begin
                        mem[wr_ptr] <= wr_data ;
                        wr_ptr <= wr_ptr + 1 ;
                    end    
            end    
    end

// ***** READ OPERATION *****
always @ (posedge rd_clk) 
    begin
        if (rst)
            rd_ptr <= 4'b0 ;
        else
            begin
                if (rd_en && !empty)
                    begin
                        rd_data <= mem[rd_ptr] ;
                        rd_ptr <= rd_ptr + 1 ;
                    end
            end
    end
// ***** Convert Binary read and write pointers to Gray code *****
assign wr_ptr_gray = wr_ptr ^ (wr_ptr >> 1) ;
assign rd_ptr_gray = rd_ptr ^ (rd_ptr >> 1) ;

// ***** Synchronize the write pointer to the read clock domain *****
always @ (posedge rd_clk) 
    begin
        if (rst) 
            begin
                wr_ptr_gray_ff1 <= 0 ;
                wr_ptr_gray_ff2 <= 0 ;
                wr_ptr_gray_sync <= 0 ;
            end
        else
            begin
                wr_ptr_gray_ff1 <= wr_ptr_gray ;
                wr_ptr_gray_ff2 <= wr_ptr_gray_ff1 ;
                wr_ptr_gray_sync <= wr_ptr_gray_ff2 ;
            end    
    end

// ***** Synchronize the read pointer to the write clock domain *****
always @ (posedge wr_clk) 
    begin
        if (rst) 
            begin
                rd_ptr_gray_ff1 <= 0 ;
                rd_ptr_gray_ff2 <= 0 ;
                rd_ptr_gray_sync <= 0 ;
            end
        else
            begin
                rd_ptr_gray_ff1 <= rd_ptr_gray ;
                rd_ptr_gray_ff2 <= rd_ptr_gray_ff1 ;
                rd_ptr_gray_sync <= rd_ptr_gray_ff2 ;
            end    
    end

// ***** EMPTY CONDITION *****
assign empty = (rd_ptr_gray == wr_ptr_gray_sync) ;

// ***** FULL CONDITION *****
assign full = (wr_ptr_gray == {~rd_ptr_gray_sync[3:2], rd_ptr_gray_sync[1:0]});

endmodule

test_1_async_fifo.v
// Write --> Faster and Read --> Slow

module test_bench ;

reg wr_clk,rd_clk,rst,wr_en,rd_en ;
reg [7:0] wr_data ; 
wire [7:0] rd_data ;
wire full,empty ;

async_fifo ASYNC_FIFO (wr_clk,rd_clk,rst,wr_en,rd_en,wr_data,rd_data,full,empty) ;

initial 
    begin
        wr_clk = 1'b0 ;
        forever 
            #5 wr_clk = ~ wr_clk ; // Write faster
    end

initial
    begin
        rd_clk = 1'b1 ;
        forever
            #10 rd_clk = ~ rd_clk ; // Read slow
    end

initial 
    begin
        $dumpfile ("FIFO.vcd") ;
        $dumpvars (0,test_bench) ;
        $monitor("wr_en=%b wr_data=%h | rd_en=%b rd_data=%h | full=%b empty=%b ",
              wr_en, wr_data, rd_en, rd_data, full, empty) ;

        rst = 1 ;
        wr_en = 0 ;
        rd_en = 0 ;
        wr_data = 8'h00 ;
        #12 ;

        rst = 0 ;

        repeat (10) 
            begin
                @(posedge wr_clk);
                if (!full) 
                    begin
                        wr_en = 1;
                        wr_data = wr_data + 1;
                    end 
                else 
                    begin
                        wr_en = 0;
                    end
            end

    wr_en = 0 ;  

    #20;
    repeat (10) 
        begin
            @(posedge rd_clk);
            if (!empty)
                rd_en = 1;
            else
                rd_en = 0;
        end

    rd_en = 0 ;

    #100 $finish ;
    end
endmodule

FIFO.vcd
$date
	Mon Jun 23 13:03:24 2025
$end
$version
	Icarus Verilog
$end
$timescale
	1s
$end
$scope module test_bench $end
$var wire 8 ! rd_data [7:0] $end
$var wire 1 " full $end
$var wire 1 # empty $end
$var reg 1 $ rd_clk $end
$var reg 1 % rd_en $end
$var reg 1 & rst $end
$var reg 1 ' wr_clk $end
$var reg 8 ( wr_data [7:0] $end
$var reg 1 ) wr_en $end
$scope module ASYNC_FIFO $end
$var wire 1 $ rd_clk $end
$var wire 1 % rd_en $end
$var wire 4 * rd_ptr_gray [3:0] $end
$var wire 1 & rst $end
$var wire 1 ' wr_clk $end
$var wire 8 + wr_data [7:0] $end
$var wire 1 ) wr_en $end
$var wire 4 , wr_ptr_gray [3:0] $end
$var wire 1 " full $end
$var wire 1 # empty $end
$var reg 8 - rd_data [7:0] $end
$var reg 4 . rd_ptr [3:0] $end
$var reg 4 / rd_ptr_gray_ff1 [3:0] $end
$var reg 4 0 rd_ptr_gray_ff2 [3:0] $end
$var reg 4 1 rd_ptr_gray_sync [3:0] $end
$var reg 4 2 wr_ptr [3:0] $end
$var reg 4 3 wr_ptr_gray_ff1 [3:0] $end
$var reg 4 4 wr_ptr_gray_ff2 [3:0] $end
$var reg 4 5 wr_ptr_gray_sync [3:0] $end
$upscope $end
$upscope $end
$enddefinitions $end
$comment Show the parameter values. $end
$dumpall
$end
#0
$dumpvars
b0 5
b0 4
b0 3
bx 2
bx 1
bx 0
bx /
b0 .
bx -
bx ,
b0 +
b0 *
0)
b0 (
0'
1&
0%
1$
1#
x"
bx !
$end
#5
0"
b0 ,
b0 2
b0 1
b0 0
b0 /
1'
#10
0'
0$
#12
0&
#15
b1 ,
b1 2
b1 (
b1 +
1)
1'
#20
b1 3
0'
1$
#25
b11 ,
b10 2
b10 (
b10 +
1'
#30
0'
0$
#35
b10 ,
b11 2
b11 (
b11 +
1'
#40
b1 4
b10 3
0'
1$
#45
b110 ,
b100 2
b100 (
b100 +
1'
#50
0'
0$
#55
b111 ,
b101 2
b101 (
b101 +
1'
#60
0#
b1 5
b10 4
b111 3
0'
1$
#65
b101 ,
b110 2
b110 (
b110 +
1'
#70
0'
0$
#75
b100 ,
b111 2
b111 (
b111 +
1'
#80
b10 5
b111 4
b100 3
0'
1$
#85
1"
b1100 ,
b1000 2
b1000 (
b1000 +
1'
#90
0'
0$
#95
0)
1'
#100
b111 5
b100 4
b1100 3
0'
1$
#105
1'
#110
0'
0$
#115
1'
#120
b100 5
b1100 4
0'
1$
#125
1'
#130
0'
0$
#135
1'
#140
b1 *
b1100 5
b1 .
b1 !
b1 -
1%
0'
1$
#145
b1 /
1'
#150
0'
0$
#155
b1 0
1'
#160
b11 *
b10 .
0'
1$
#165
0"
b1 1
b11 /
1'
#170
0'
0$
#175
b11 0
1'
#180
b10 *
b11 .
b11 !
b11 -
0'
1$
#185
b11 1
b10 /
1'
#190
0'
0$
#195
b10 0
1'
#200
b110 *
b100 .
0'
1$
#205
b10 1
b110 /
1'
#210
0'
0$
#215
b110 0
1'
#220
b111 *
b101 .
b101 !
b101 -
0'
1$
#225
b110 1
b111 /
1'
#230
0'
0$
#235
b111 0
1'
#240
b101 *
b110 .
0'
1$
#245
b111 1
b101 /
1'
#250
0'
0$
#255
b101 0
1'
#260
b100 *
b111 .
b111 !
b111 -
0'
1$
#265
b101 1
b100 /
1'
#270
0'
0$
#275
b100 0
1'
#280
1#
b1100 *
b1000 .
0'
1$
#285
b100 1
b1100 /
1'
#290
0'
0$
#295
b1100 0
1'
#300
0%
0'
1$
#305
b1100 1
1'
